pytorch_ner/__init__.py
pytorch_ner/__main__.py
pytorch_ner/config.py
pytorch_ner/dataset.py
pytorch_ner/logger.py
pytorch_ner/main.py
pytorch_ner/metrics.py
pytorch_ner/onnx.py
pytorch_ner/prepare_data.py
pytorch_ner/save.py
pytorch_ner/train.py
pytorch_ner/utils.py
pytorch_ner/nn_modules/__init__.py
pytorch_ner/nn_modules/architecture.py
pytorch_ner/nn_modules/attention.py
pytorch_ner/nn_modules/dropout.py
pytorch_ner/nn_modules/embedding.py
pytorch_ner/nn_modules/linear.py
pytorch_ner/nn_modules/normalization.py
pytorch_ner/nn_modules/rnn.py
tests/__init__.py
tests/test_dataset.py
tests/test_main.py
tests/test_onnx.py
tests/test_prepare_data.py
tests/test_save.py
tests/test_train.py
tests/test_nn_modules/__init__.py
tests/test_nn_modules/test_architecture.py
tests/test_nn_modules/test_attention.py
tests/test_nn_modules/test_dropout.py
tests/test_nn_modules/test_embedding.py
tests/test_nn_modules/test_linear.py
tests/test_nn_modules/test_normalization.py
tests/test_nn_modules/test_rnn.py
pytorch_ner-0.1.0.dist-info/LICENSE
pytorch_ner-0.1.0.dist-info/METADATA
pytorch_ner-0.1.0.dist-info/WHEEL
pytorch_ner-0.1.0.dist-info/entry_points.txt
pytorch_ner-0.1.0.dist-info/top_level.txt
pytorch_ner-0.1.0.dist-info/RECORD
