Metadata-Version: 2.1
Name: pytorch-ner
Version: 0.1.0
Summary: Pipeline for training NER models using PyTorch
Home-page: https://github.com/dayyass/pytorch-ner
Author: Dani El-Ayyass
Author-email: dayyass@yandex.ru
License: UNKNOWN
Project-URL: Bug Tracker, https://github.com/dayyass/pytorch-ner/issues
Platform: UNKNOWN
Classifier: Programming Language :: Python :: 3
Classifier: License :: OSI Approved :: MIT License
Classifier: Operating System :: OS Independent
Requires-Python: >=3.6
License-File: LICENSE
Requires-Dist: gensim (==3.8.3)
Requires-Dist: numpy (>=1.19.5)
Requires-Dist: onnx (>=1.10.1)
Requires-Dist: onnxruntime (>=1.9.0)
Requires-Dist: PyYAML (>=5.4.1)
Requires-Dist: scikit-learn (>=0.24.2)
Requires-Dist: torch (>=1.9.1)
Requires-Dist: tqdm (>=4.62.3)
